rclone_filesystem/__init__.py
rclone_filesystem-0.1.0.dist-info/METADATA
rclone_filesystem-0.1.0.dist-info/WHEEL
rclone_filesystem-0.1.0.dist-info/licenses/LICENSE
rclone_filesystem-0.1.0.dist-info/RECORD
