Metadata-Version: 2.4
Name: rclone-filesystem
Version: 0.1.0
Summary: A Python package for integrating rclone with fsspec
Project-URL: Repository, https://github.com/zincware/rclone-filesystem
Project-URL: Releases, https://github.com/zincware/rclone-filesystem/releases
Project-URL: Discord, https://discord.gg/7ncfwhsnm4
Author-email: Fabian Zills <fzills@icp.uni-stuttgart.de>
License-Expression: Apache-2.0
License-File: LICENSE
Requires-Python: >=3.11
Requires-Dist: fsspec>=2025.5.1
Requires-Dist: rclone-python>=0.1.21
